LICENSE.txt
MANIFEST.in
README.md
setup.cfg
setup.py
redbird_sdk/__init__.py
redbird_sdk/apirequests.py
redbird_sdk/apiresponses.py
redbird_sdk/exceptions.py
redbird_sdk/rb_utils.py
redbird_sdk/restclient.py
redbird_sdk/rftradingapi.py
redbird_sdk/tradingapi.py
redbird_sdk_python.egg-info/PKG-INFO
redbird_sdk_python.egg-info/SOURCES.txt
redbird_sdk_python.egg-info/dependency_links.txt
redbird_sdk_python.egg-info/requires.txt
redbird_sdk_python.egg-info/top_level.txt